CONTRIBUTING.md
MANIFEST.in
README
README.rst
TERMS.md
setup.py
django_html_cleaner/__init__.py
django_html_cleaner/cleaner.py
django_html_cleaner/models.py
django_html_cleaner.egg-info/PKG-INFO
django_html_cleaner.egg-info/SOURCES.txt
django_html_cleaner.egg-info/dependency_links.txt
django_html_cleaner.egg-info/requires.txt
django_html_cleaner.egg-info/top_level.txt
tests/__init__.py
tests/models.py
tests/test_cleaner.py
tests/test_models.py