Metadata-Version: 1.0
Name: django-html-cleaner
Version: 0.2.3
Summary: Django text and character fields that clean HTML input.
Home-page: https://github.com/cndreisbach/django-html-cleaner
Author: Clinton Dreisbach
Author-email: clinton.dreisbach@cfpb.gov
License: Public Domain / CC0
Platform: UNKNOWN
